recursor_sdk/__init__.py
recursor_sdk/__main__.py
recursor_sdk/cli.py
recursor_sdk/client.py
recursor_sdk/websocket.py
recursor_sdk/clients/__init__.py
recursor_sdk/clients/activity_logs.py
recursor_sdk/clients/auth.py
recursor_sdk/clients/billing.py
recursor_sdk/clients/codebase.py
recursor_sdk/clients/corrections.py
recursor_sdk/clients/enterprise.py
recursor_sdk/clients/gateway.py
recursor_sdk/clients/intelligence.py
recursor_sdk/clients/memory.py
recursor_sdk/clients/notifications.py
recursor_sdk/clients/projects.py
recursor_sdk/clients/proxy.py
recursor_sdk/clients/settings.py
recursor_sdk/clients/synchronization.py
recursor_sdk/clients/workflows.py
recursor_sdk/templates/ingest.py
recursor_sdk-1.0.2.dist-info/METADATA
recursor_sdk-1.0.2.dist-info/WHEEL
recursor_sdk-1.0.2.dist-info/entry_points.txt
recursor_sdk-1.0.2.dist-info/licenses/LICENSE
recursor_sdk-1.0.2.dist-info/RECORD
