Metadata-Version: 2.4
Name: recursor-sdk
Version: 1.0.2
Summary: Official Python SDK for Recursor - Memory system for LLMs that ensures lasting context, consistency, and learning across sessions
Project-URL: Homepage, https://recursor.dev
Project-URL: Documentation, https://docs.recursor.dev
Project-URL: Repository, https://github.com/luvbird32/recursor
Project-URL: Issues, https://github.com/luvbird32/recursor/issues
Project-URL: Changelog, https://github.com/luvbird32/recursor/blob/main/CHANGELOG.md
Author-email: Recursor <team@recursor.dev>
Maintainer-email: Recursor <team@recursor.dev>
License-File: LICENSE
Keywords: ai,api,artificial-intelligence,chatgpt,claude,code-intelligence,context,corrections,llm,machine-learning,memory,openai,recursor,sdk,websocket
Classifier: Development Status :: 4 - Beta
Classifier: Intended Audience :: Developers
Classifier: License :: OSI Approved :: MIT License
Classifier: Operating System :: OS Independent
Classifier: Programming Language :: Python :: 3
Classifier: Programming Language :: Python :: 3.9
Classifier: Programming Language :: Python :: 3.10
Classifier: Programming Language :: Python :: 3.11
Classifier: Programming Language :: Python :: 3.12
Classifier: Topic :: Internet :: WWW/HTTP :: Dynamic Content
Classifier: Topic :: Scientific/Engineering :: Artificial Intelligence
Classifier: Topic :: Software Development :: Libraries
Classifier: Topic :: Software Development :: Libraries :: Python Modules
Classifier: Typing :: Typed
Requires-Python: >=3.9
Requires-Dist: httpx<1,>=0.25
Requires-Dist: websockets<13,>=12.0
Provides-Extra: test
Requires-Dist: pytest-asyncio>=0.21.0; extra == 'test'
Requires-Dist: pytest-cov>=4.1.0; extra == 'test'
Requires-Dist: pytest>=7.4.0; extra == 'test'
